vMFD/__init__.py
vMFD-0.2.dist-info/LICENSE
vMFD-0.2.dist-info/METADATA
vMFD-0.2.dist-info/WHEEL
vMFD-0.2.dist-info/top_level.txt
vMFD-0.2.dist-info/RECORD
