Metadata-Version: 2.1
Name: vMFD
Version: 0.2
Summary: Infer moral appeals from text
Home-page: https://github.com/ZeningDuan/vMFD
Author: Kai-Cheng Yang <yang3kc@gmail.com>, Zening Duan <zening.duan@wisc.edu>
License: MIT
License-File: LICENSE
Requires-Dist: pandas
